bibtutils/__init__.py
bibtutils/version.py
bibtutils/gcp/__init__.py
bibtutils/gcp/bigquery.py
bibtutils/gcp/iam.py
bibtutils/gcp/pubsub.py
bibtutils/gcp/secrets.py
bibtutils/gcp/storage.py
bibtutils/slack/__init__.py
bibtutils/slack/error.py
bibtutils/slack/message.py
bibtutils-2.0.1.dist-info/METADATA
bibtutils-2.0.1.dist-info/WHEEL
bibtutils-2.0.1.dist-info/licenses/LICENSE
bibtutils-2.0.1.dist-info/RECORD
